{
  "gitSyncId": "692f23e7862bc92544420b37_b38f88f0-df37-49a3-b34e-b3d94584a767",
  "id": "Resultados_Qry_pontuacaoIndicador",
  "pluginId": "postgres-plugin",
  "pluginType": "DB",
  "unpublishedAction": {
    "actionConfiguration": {
      "body": "SELECT * FROM vw_score_user_avg_indicador\nWHERE id_utilizador = {{Select_utilizador.selectedOptionValue}}\nAND ano = {{Select_year.selectedOptionValue}} OR ({{Select_year.selectedOptionValue }}) = '';",
      "encodeParamsToggle": true,
      "paginationType": "NONE",
      "pluginSpecifiedTemplates": [
        {
          "value": true
        }
      ],
      "timeoutInMillisecond": 10000
    },
    "confirmBeforeExecute": false,
    "datasource": {
      "id": "pg_alquevaustentavel",
      "isAutoGenerated": false,
      "name": "pg_alquevaustentavel",
      "pluginId": "postgres-plugin"
    },
    "dynamicBindingPathList": [
      {
        "key": "body"
      }
    ],
    "name": "Qry_pontuacaoIndicador",
    "pageId": "Resultados",
    "runBehaviour": "AUTOMATIC",
    "userSetOnLoad": true
  }
}